pyboxen/__init__.py
pyboxen/main.py
pyboxen-1.2.0.dist-info/LICENSE
pyboxen-1.2.0.dist-info/WHEEL
pyboxen-1.2.0.dist-info/METADATA
pyboxen-1.2.0.dist-info/RECORD
