Metadata-Version: 2.1
Name: pyboxen
Version: 1.2.0
Summary: Beautiful, customizable boxes in your terminal using Python
Home-page: https://github.com/savioxavier/pyboxen
License: MIT
Author: Skyascii
Author-email: savioxavier112@gmail.com
Requires-Python: >=3.8.0,<4.0.0
Classifier: License :: OSI Approved :: MIT License
Classifier: Programming Language :: Python :: 3
Classifier: Programming Language :: Python :: 3.10
Classifier: Programming Language :: Python :: 3.8
Classifier: Programming Language :: Python :: 3.9
Requires-Dist: rich (>=12.5.1)
Project-URL: Repository, https://github.com/savioxavier/pyboxen
